LICENSE.txt
MANIFEST.in
README.md
setup.cfg
setup.py
croppie/__init__.py
croppie/apps.py
croppie/fields.py
croppie/models.py
croppie/views.py
croppie/migrations/__init__.py
croppie/static/croppie/croppie.css
croppie/static/croppie/croppie.min.js
croppie/static/croppie/form-process.js
croppie/templates/croppie/widget.html
croppie/widgets/__init__.py
croppie/widgets/base.py
croppie/widgets/widgets.py
croppie/widgets/widgets_old.py
django_croppie.egg-info/PKG-INFO
django_croppie.egg-info/SOURCES.txt
django_croppie.egg-info/dependency_links.txt
django_croppie.egg-info/top_level.txt