Metadata-Version: 1.1
Name: django-croppie
Version: 1.2
Summary: Application for easy croppie.js integration to django
Home-page: https://github.com/dima-kov/django-croppie
Author: Dima Kovalchuk
Author-email: dmyutro@ukr.net
License: MIT
Download-URL: https://github.com/dima-kov/django-croppie/archive/v1.2.tar.gz
Keywords: python,django,croppie,croppie.js,image-processing,image-cropping
Platform: UNKNOWN
Classifier: Environment :: Web Environment
Classifier: Framework :: Django
Classifier: Framework :: Django :: 1.8
Classifier: Framework :: Django :: 1.9
Classifier: Framework :: Django :: 1.10
Classifier: Framework :: Django :: 1.11
Classifier: Intended Audience :: Developers
Classifier: License :: OSI Approved :: MIT License
Classifier: Operating System :: OS Independent
Classifier: Programming Language :: Python
Classifier: Programming Language :: Python :: 2
Classifier: Programming Language :: Python :: 2.7
Classifier: Programming Language :: Python :: 3
Classifier: Programming Language :: Python :: 3.4
Classifier: Programming Language :: Python :: 3.5
Classifier: Topic :: Internet :: WWW/HTTP
Classifier: Topic :: Internet :: WWW/HTTP :: Dynamic Content
